twitterhal/__init__.py
twitterhal/command_line.py
twitterhal/database.py
twitterhal/engine.py
twitterhal/gracefulkiller.py
twitterhal/models.py
twitterhal/runtime.py
twitterhal/twitter_api.py
twitterhal/util.py
twitterhal/conf/__init__.py
twitterhal/conf/default_settings.py
twitterhal-0.7.3.dist-info/LICENSE
twitterhal-0.7.3.dist-info/METADATA
twitterhal-0.7.3.dist-info/WHEEL
twitterhal-0.7.3.dist-info/entry_points.txt
twitterhal-0.7.3.dist-info/top_level.txt
twitterhal-0.7.3.dist-info/RECORD
