Metadata-Version: 2.1
Name: twitterhal
Version: 0.7.3
Summary: A MegaHAL bot for Twitter
Home-page: https://github.com/Eboreg/twitterhal
Author: Robert Huselius
Author-email: robert@huseli.us
License: UNKNOWN
Platform: UNKNOWN
Classifier: Programming Language :: Python :: 3
Classifier: License :: OSI Approved :: GNU General Public License v3 (GPLv3)
Classifier: Operating System :: OS Independent
Classifier: Development Status :: 3 - Alpha
Classifier: Environment :: Console
Classifier: Intended Audience :: Developers
Classifier: Topic :: Communications
Classifier: Topic :: Internet
Classifier: Topic :: Scientific/Engineering :: Artificial Intelligence
Classifier: Topic :: Software Development :: Libraries :: Python Modules
Classifier: Topic :: Text Processing :: Linguistic
Requires-Python: >=3.6
Requires-Dist: emoji
Requires-Dist: megahal (>=0.3.4)
Requires-Dist: python-Levenshtein
Requires-Dist: python-twitter
Provides-Extra: detectlanguage
Requires-Dist: detectlanguage ; extra == 'detectlanguage'
Provides-Extra: redis
Requires-Dist: hiredis ; extra == 'redis'
Requires-Dist: redis (>=3) ; extra == 'redis'
